{
  "project_info": {
    "project_number": "117446866554",
    "project_id": "taskmanagerapp-d2516",
    "storage_bucket": "taskmanagerapp-d2516.firebasestorage.app"
  },
  "client": [
    {
      "client_info": {
        "mobilesdk_app_id": "1:117446866554:android:293bd2a7313112fc7eedc3",
        "android_client_info": {
          "package_name": "com.example.task_manager_app"
        }
      },
      "oauth_client": [],
      "api_key": [
        {
          "current_key": "AIzaSyDXZ-BsMi5eo9yKuhFnrN9bYRAT8x1IRg4"
        }
      ],
      "services": {
        "appinvite_service": {
          "other_platform_oauth_client": []
        }
      }
    }
  ],
  "configuration_version": "1"
}